LICENSE
MANIFEST.in
README.rst
setup.py
django_shop_wspay.egg-info/PKG-INFO
django_shop_wspay.egg-info/SOURCES.txt
django_shop_wspay.egg-info/dependency_links.txt
django_shop_wspay.egg-info/not-zip-safe
django_shop_wspay.egg-info/requires.txt
django_shop_wspay.egg-info/top_level.txt
docs/Makefile
docs/conf.py
docs/index.rst
docs/make.bat
requirements/base.txt
requirements/docs.txt
requirements/test.txt
shop_wspay/__init__.py
shop_wspay/forms.py
shop_wspay/models.py
shop_wspay/settings.py
shop_wspay/wspay.py
shop_wspay/templates/shop_wspay/base.html
shop_wspay/templates/shop_wspay/cancel.html
shop_wspay/templates/shop_wspay/error.html
shop_wspay/templates/shop_wspay/failed.html
shop_wspay/templates/shop_wspay/pay.html
tests/__init__.py
tests/settings.py
tests/urls.py
tests/shop_wspay/__init__.py