Metadata-Version: 1.1
Name: django-shop-wspay
Version: 0.0.2
Summary: WSPay payment gateway implementation for django-shop
Home-page: http://pypi.python.org/pypi/django-shop-wspay/
Author: Dino Perovic
Author-email: dino.perovic@gmail.com
License: BSD
Platform: UNKNOWN
Classifier: Development Status :: 3 - Alpha
Classifier: Environment :: Web Environment
Classifier: Framework :: Django
Classifier: Intended Audience :: Developers
Classifier: Operating System :: OS Independent
Classifier: Programming Language :: Python
Classifier: Topic :: Internet :: WWW/HTTP
